niluclient/__init__.py
niluclient-0.1.2.dist-info/LICENSE
niluclient-0.1.2.dist-info/METADATA
niluclient-0.1.2.dist-info/WHEEL
niluclient-0.1.2.dist-info/top_level.txt
niluclient-0.1.2.dist-info/RECORD
