Metadata-Version: 2.1
Name: niluclient
Version: 0.1.2
Summary: An API client for getting pollution data from NILU sensor stations in Norway.
Home-page: https://github.com/hfurubotten/niluclient
Author: Heine Furubotten
License: MIT
Platform: UNKNOWN
Classifier: Programming Language :: Python :: 3
Classifier: License :: OSI Approved :: MIT License
Classifier: Operating System :: OS Independent
